[
    {
        "client_msg_id": "23C63346-3AC4-4A1C-8725-89BEF84F1A20",
        "type": "message",
        "text": "VROOM VROOM",
        "user": "UU50D077H",
        "ts": "1597010082.000300",
        "team": "TS2PZ9PJR",
        "user_team": "TS2PZ9PJR",
        "source_team": "TS2PZ9PJR",
        "user_profile": {
            "avatar_hash": "790b5f83cbe4",
            "image_72": "https:\/\/avatars.slack-edge.com\/2020-02-16\/943684986291_790b5f83cbe4b100e623_72.jpg",
            "first_name": "Jake",
            "real_name": "Jake Enos",
            "display_name": "Jake Enos",
            "team": "TS2PZ9PJR",
            "name": "jake",
            "is_restricted": false,
            "is_ultra_restricted": false
        },
        "blocks": [
            {
                "type": "rich_text",
                "block_id": "150",
                "elements": [
                    {
                        "type": "rich_text_section",
                        "elements": [
                            {
                                "type": "text",
                                "text": "VROOM VROOM"
                            }
                        ]
                    }
                ]
            }
        ],
        "reactions": [
            {
                "name": "butterfly",
                "users": [
                    "US2PZ9QBF",
                    "UU50D077H",
                    "URRA07VU3"
                ],
                "count": 3
            }
        ]
    },
    {
        "client_msg_id": "00D9B89F-9D30-4E83-AFAE-E246B81AE06F",
        "type": "message",
        "text": "VROOM VROOM",
        "user": "US2PZ9QBF",
        "ts": "1597010084.000400",
        "team": "TS2PZ9PJR",
        "user_team": "TS2PZ9PJR",
        "source_team": "TS2PZ9PJR",
        "user_profile": {
            "avatar_hash": "g2a1bd0cf75b",
            "image_72": "https:\/\/secure.gravatar.com\/avatar\/2a1bd0cf75be1ecad038b410434ec640.jpg?s=72&d=https%3A%2F%2Fa.slack-edge.com%2Fdf10d%2Fimg%2Favatars%2Fava_0017-72.png",
            "first_name": "Matthew",
            "real_name": "Matthew Pickerell",
            "display_name": "",
            "team": "TS2PZ9PJR",
            "name": "pickerell",
            "is_restricted": false,
            "is_ultra_restricted": false
        },
        "blocks": [
            {
                "type": "rich_text",
                "block_id": "xfohv",
                "elements": [
                    {
                        "type": "rich_text_section",
                        "elements": [
                            {
                                "type": "text",
                                "text": "VROOM VROOM"
                            }
                        ]
                    }
                ]
            }
        ],
        "reactions": [
            {
                "name": "ultrafastparrot",
                "users": [
                    "US2PZ9QBF",
                    "UU50D077H",
                    "URRA07VU3"
                ],
                "count": 3
            }
        ]
    }
]